lark_oapi_compact/__init__.py
lark_oapi_compact/remaintain/LICENSE
lark_oapi_compact/remaintain/README.md
lark_oapi_compact/remaintain/README.zh.md
lark_oapi_compact/remaintain/__init__.py
lark_oapi_compact/remaintain/extra/__init__.py
lark_oapi_compact/remaintain/extra/app_settings.py
lark_oapi_compact/remaintain/extra/config.py
lark_oapi_compact/remaintain/extra/consts.py
lark_oapi_compact/remaintain/extra/context.py
lark_oapi_compact/remaintain/extra/logger.py
lark_oapi_compact/remaintain/extra/store.py
lark_oapi_compact/remaintain/extra/api/__init__.py
lark_oapi_compact/remaintain/extra/api/api_error.py
lark_oapi_compact/remaintain/extra/api/tokens.py
lark_oapi_compact/remaintain/extra/api/request/__init__.py
lark_oapi_compact/remaintain/extra/api/request/form_data.py
lark_oapi_compact/remaintain/extra/api/request/request.py
lark_oapi_compact/remaintain/extra/api/response/__init__.py
lark_oapi_compact/remaintain/extra/api/response/response.py
lark_oapi_compact/remaintain/extra/card/__init__.py
lark_oapi_compact/remaintain/extra/card/card.py
lark_oapi_compact/remaintain/extra/card/handler/__init__.py
lark_oapi_compact/remaintain/extra/card/handler/handlers.py
lark_oapi_compact/remaintain/extra/card/handler/manager.py
lark_oapi_compact/remaintain/extra/card/model/__init__.py
lark_oapi_compact/remaintain/extra/card/model/card.py
lark_oapi_compact/remaintain/extra/card/model/error.py
lark_oapi_compact/remaintain/extra/event/__init__.py
lark_oapi_compact/remaintain/extra/event/event.py
lark_oapi_compact/remaintain/extra/event/app/__init__.py
lark_oapi_compact/remaintain/extra/event/app/ticket.py
lark_oapi_compact/remaintain/extra/event/handler/__init__.py
lark_oapi_compact/remaintain/extra/event/handler/handlers.py
lark_oapi_compact/remaintain/extra/event/handler/manager.py
lark_oapi_compact/remaintain/extra/event/model/__init__.py
lark_oapi_compact/remaintain/extra/event/model/error.py
lark_oapi_compact/remaintain/extra/event/model/event.py
lark_oapi_compact-0.1.3.dist-info/METADATA
lark_oapi_compact-0.1.3.dist-info/WHEEL
lark_oapi_compact-0.1.3.dist-info/licenses/LICENSE
lark_oapi_compact-0.1.3.dist-info/RECORD
