Metadata-Version: 2.1
Name: lark-oapi-compact
Version: 0.1.3
Summary: Lark OpenAPI SDK for Python
Project-URL: Repository, https://github.com/StrayDragon/oapi-sdk-python-compact
Project-URL: Documentation, https://github.com/StrayDragon/oapi-sdk-python-compact/blob/main/README.md
Project-URL: Changelog, https://github.com/StrayDragon/oapi-sdk-python-compact/blob/main/CHANGELOG.md
Author-email: L8ng <straydragonl@foxmail.com>
License: MIT
License-File: LICENSE
Keywords: feishu,lark
Classifier: Development Status :: 4 - Beta
Classifier: License :: OSI Approved :: MIT License
Classifier: Operating System :: OS Independent
Classifier: Programming Language :: Python
Classifier: Programming Language :: Python :: 3 :: Only
Classifier: Programming Language :: Python :: 3.7
Classifier: Topic :: Software Development :: Libraries :: Python Modules
Requires-Python: >=3.7
Requires-Dist: attrs>=23.2.0
Requires-Dist: lark-oapi==1.3.4
Requires-Dist: pycryptodome>=3.20.0
Requires-Dist: pydantic==1.10.18
Requires-Dist: requests>=2.31.0
Requires-Dist: typing-extensions
